LICENSE
README.md
setup.cfg
setup.py
GANetic.egg-info/PKG-INFO
GANetic.egg-info/SOURCES.txt
GANetic.egg-info/dependency_links.txt
GANetic.egg-info/requires.txt
GANetic.egg-info/top_level.txt
ganetic/__init__.py
ganetic/basemodel.py
ganetic/cgan.py
ganetic/cyclegan.py
ganetic/dcgan.py
ganetic/pix2pix.py
ganetic/srgan.py
ganetic/layers/__init__.py
ganetic/layers/blocks.py