Metadata-Version: 2.1
Name: GANetic
Version: 0.0.8
Summary: A Collection of GANs - PyTorch
Home-page: https://github.com/kingjuno/GANetic
Author: Geo Jolly
Author-email: geojollyc@gmail.com
License: MIT
Keywords: GAN,Generative Adversarial Networks,Deep Learning,PyTorch,GANetic,Generative Artificial Intelligence
Platform: UNKNOWN
Classifier: Development Status :: 4 - Beta
Classifier: Intended Audience :: Developers
Classifier: Intended Audience :: Science/Research
Classifier: Topic :: Scientific/Engineering :: Artificial Intelligence
Classifier: License :: OSI Approved :: MIT License
Classifier: Programming Language :: Python :: 3.6
License-File: LICENSE
